aspen_sentry.py
distribute_setup.py
setup.py
aspen_sentry.egg-info/PKG-INFO
aspen_sentry.egg-info/SOURCES.txt
aspen_sentry.egg-info/dependency_links.txt
aspen_sentry.egg-info/not-zip-safe
aspen_sentry.egg-info/requires.txt
aspen_sentry.egg-info/top_level.txt