Metadata-Version: 1.0
Name: aspen-sentry
Version: 1.0.0
Summary: Sentry plugin for Aspen
Home-page: http://aspen.io/
Author: Chad Whitacre
Author-email: chad@zetaweb.com
License: UNKNOWN
Platform: UNKNOWN
